ryanvk_rye-0.1.1.dist-info/METADATA
ryanvk_rye-0.1.1.dist-info/WHEEL
rye/__init__.py
rye/_capability.py
rye/_runtime.py
rye/builtins/__init__.py
rye/builtins/instance_of.py
rye/builtins/lifespan.py
rye/builtins/overloads.py
rye/collector.py
rye/entity.py
rye/fn/__init__.py
rye/fn/base.py
rye/fn/compose.py
rye/fn/entity.py
rye/fn/overload.py
rye/fn/record.py
rye/layout.py
rye/operators.py
rye/perform.py
rye/topic.py
rye/typing.py
rye/utils.py
ryanvk_rye-0.1.1.dist-info/RECORD
